giskard_vision/__init__.py
giskard_vision/core/__init__.py
giskard_vision/core/issues.py
giskard_vision/core/logger.py
giskard_vision/core/types.py
giskard_vision/core/dataloaders/base.py
giskard_vision/core/dataloaders/hf.py
giskard_vision/core/dataloaders/meta.py
giskard_vision/core/dataloaders/tf.py
giskard_vision/core/dataloaders/utils.py
giskard_vision/core/dataloaders/wrappers.py
giskard_vision/core/detectors/base.py
giskard_vision/core/detectors/blur_detector.py
giskard_vision/core/detectors/color_detector.py
giskard_vision/core/detectors/decorator.py
giskard_vision/core/detectors/example_manager.py
giskard_vision/core/detectors/metadata_detector.py
giskard_vision/core/detectors/noise_detector.py
giskard_vision/core/detectors/perturbation.py
giskard_vision/core/detectors/specs.py
giskard_vision/core/models/base.py
giskard_vision/core/models/hf_pipeline.py
giskard_vision/core/scanner/__init__.py
giskard_vision/core/scanner/scanner.py
giskard_vision/core/tests/__init__.py
giskard_vision/core/tests/base.py
giskard_vision/core/transformations/resize.py
giskard_vision/core/utils/__init__.py
giskard_vision/core/utils/errors.py
giskard_vision/image_classification/__init__.py
giskard_vision/image_classification/types.py
giskard_vision/image_classification/dataloaders/__init__.py
giskard_vision/image_classification/dataloaders/loaders.py
giskard_vision/image_classification/detectors/__init__.py
giskard_vision/image_classification/detectors/metadata_detector.py
giskard_vision/image_classification/detectors/specs.py
giskard_vision/image_classification/models/__init__.py
giskard_vision/image_classification/models/base.py
giskard_vision/image_classification/models/wrappers.py
giskard_vision/image_classification/tests/performance.py
giskard_vision/landmark_detection/__init__.py
giskard_vision/landmark_detection/types.py
giskard_vision/landmark_detection/dataloaders/__init__.py
giskard_vision/landmark_detection/dataloaders/base.py
giskard_vision-1.0.0.dist-info/LICENSE
giskard_vision-1.0.0.dist-info/METADATA
giskard_vision-1.0.0.dist-info/WHEEL
giskard_vision-1.0.0.dist-info/top_level.txt
giskard_vision-1.0.0.dist-info/RECORD
