Metadata-Version: 2.1
Name: giskard-vision
Version: 1.0.0
Summary: The expansion of Giskard into testing computer vision models
Author-email: Giskard AI <hello@giskard.ai>
Requires-Python: <3.12,>=3.10
License-File: LICENSE
Requires-Dist: opencv-python
Requires-Dist: numpy<2
Requires-Dist: pillow>=10.4.0
Requires-Dist: scikit-learn>=1.5.1
Requires-Dist: pandas>=2.2.2
